infrared_tripleo_overcloud-3.0.0.dist-info/DESCRIPTION.rst
infrared_tripleo_overcloud-3.0.0.dist-info/METADATA
infrared_tripleo_overcloud-3.0.0.dist-info/RECORD
infrared_tripleo_overcloud-3.0.0.dist-info/WHEEL
infrared_tripleo_overcloud-3.0.0.dist-info/entry_points.txt
infrared_tripleo_overcloud-3.0.0.dist-info/metadata.json
infrared_tripleo_overcloud-3.0.0.dist-info/pbr.json
infrared_tripleo_overcloud-3.0.0.dist-info/top_level.txt
tripleo_overcloud/__init__.py
tripleo_overcloud/build_templates.yml
tripleo_overcloud/clouds.yml
tripleo_overcloud/collect-ansible-facts.yml
tripleo_overcloud/composable_roles.yml
tripleo_overcloud/create_external_network.yml
tripleo_overcloud/deploy.yml
tripleo_overcloud/docker_after_workaround.yml
tripleo_overcloud/forward_overcloud_dashboard.yml
tripleo_overcloud/hypervisor.yml
tripleo_overcloud/install.yml
tripleo_overcloud/introspect.yml
tripleo_overcloud/loadbalancer.yml
tripleo_overcloud/main.yml
tripleo_overcloud/ovb.yml
tripleo_overcloud/overcloud_reboot.yml
tripleo_overcloud/plugin.spec
tripleo_overcloud/post.yml
tripleo_overcloud/pre.yml
tripleo_overcloud/splitstack.yml
tripleo_overcloud/tag.yml
tripleo_overcloud/tempest_deployer_input.yml
tripleo_overcloud/tls_everywhere.yml
tripleo_overcloud/tripleo_roles.yml
tripleo_overcloud/update.yml
tripleo_overcloud/update_inventory.yml
tripleo_overcloud/upgrade.yml
tripleo_overcloud/validate.yml
tripleo_overcloud/version.yml
tripleo_overcloud/files/config_lvm.yaml
tripleo_overcloud/files/debug.yaml
tripleo_overcloud/files/roles/composition/controller.yml
tripleo_overcloud/files/roles/composition/database.yml
tripleo_overcloud/files/roles/composition/messaging.yml
tripleo_overcloud/files/roles/composition/networker.yml
tripleo_overcloud/files/roles/database/controller.yml
tripleo_overcloud/files/roles/database/database.yml
tripleo_overcloud/files/roles/database-messaging/controller.yml
tripleo_overcloud/files/roles/database-messaging/database.yml
tripleo_overcloud/files/roles/database-messaging/messaging.yml
tripleo_overcloud/files/roles/database-messaging-networker/controller.yml
tripleo_overcloud/files/roles/database-messaging-networker/database.yml
tripleo_overcloud/files/roles/database-messaging-networker/messaging.yml
tripleo_overcloud/files/roles/database-messaging-networker/networker.yml
